{
  "kind": "collectionType",
  "collectionName": "malla_curricular",
  "info": {
    "name": "Componentes Curriculares",
    "description": ""
  },
  "options": {
    "increments": true,
    "timestamps": true,
    "draftAndPublish": true
  },
  "pluginOptions": {},
  "attributes": {
    "nombre_componente": {
      "type": "string"
    },
    "file": {
      "model": "file",
      "via": "related",
      "allowedTypes": [
        "files"
      ],
      "plugin": "upload",
      "required": false,
      "pluginOptions": {}
    }
  }
}
